{
  "latest_draw": 1208,
  "next_draw": 1209,
  "exclusion_list": [
    27,
    45,
    12,
    3,
    33,
    38,
    1,
    18,
    16,
    34
  ],
  "predictions": [
    [
      5,
      14,
      22,
      25,
      32,
      44
    ],
    [
      2,
      9,
      19,
      32,
      36,
      44
    ],
    [
      5,
      15,
      18,
      25,
      32,
      41
    ],
    [
      9,
      23,
      28,
      37,
      41,
      44
    ],
    [
      2,
      5,
      19,
      20,
      25,
      43
    ]
  ],
  "generated_at": "2026-01-25 01:32:22",
  "pattern_summary": {
    "top_odd_even": "3:3",
    "top_ac": 8,
    "top_cons": 0
  }
}